vvspy/__init__.py
vvspy/arrivals.py
vvspy/departures.py
vvspy/trip.py
vvspy/enums/__init__.py
vvspy/enums/stations.py
vvspy/models/__init__.py
vvspy/models/arrival.py
vvspy/models/connection.py
vvspy/models/departure.py
vvspy/models/destination.py
vvspy/models/line_operator.py
vvspy/models/origin.py
vvspy/models/serving_line.py
vvspy/models/transportation.py
vvspy/models/trip.py
vvspy-2.3.1.dist-info/licenses/LICENSE
vvspy-2.3.1.dist-info/METADATA
vvspy-2.3.1.dist-info/WHEEL
vvspy-2.3.1.dist-info/top_level.txt
vvspy-2.3.1.dist-info/RECORD
